niuload/__init__.py
niuload/balanced_load.py
niuload-0.2.4.dist-info/METADATA
niuload-0.2.4.dist-info/WHEEL
niuload-0.2.4.dist-info/top_level.txt
niuload-0.2.4.dist-info/RECORD
