Metadata-Version: 2.1
Name: niuload
Version: 0.2.4
Summary: A module for balanced loading of large language models
Home-page: https://github.com/NiuTrans/NiuLoad
Author: rangehow
Author-email: rangehow@outlook.com
Classifier: Programming Language :: Python :: 3
Classifier: License :: OSI Approved :: MIT License
Classifier: Operating System :: OS Independent
Requires-Python: >=3.6
Requires-Dist: accelerate
Requires-Dist: transformers
Requires-Dist: torch
